[
  {
    "name": "螺旋桨",
    "type":1,
    "id":0,
    "son": [
      {
        "name": "转速(r/min)",
        "value": "100"
      },
      {
        "name": "压力(bar)",
        "value": "100"
      },
      {
        "name": "扭矩(kN/m)",
        "value": "100"
      },
      {
        "name": "开度(mm)",
        "value": "100"
      },
      {
        "name": "油温(DEG.C)",
        "value": "100"
      }
    ]
  },
  {
    "name": "刀盘情况",
    "type":1,
    "id":1,
    "son": [
      {
        "name": "油缸A行程(mm)",
        "value": 100
      },
      {
        "name": "油缸B行程(mm)",
        "value": 100
      },
      {
        "name": "油缸C行程(mm)",
        "value": 100
      },
      {
        "name": "油缸D行程(mm)",
        "value": 100
      },
      {
        "name": "油缸A压力(bar)",
        "value": 100
      },
      {
        "name": "油缸B压力(bar)",
        "value": 100
      },
      {
        "name": "油缸C压力(bar)",
        "value": 100
      },
      {
        "name": "油缸D压力(bar)",
        "value": 100
      }
    ]
  },
  {
    "name": "铰链情况",
    "type":1,
    "id":2,
    "son": [
      {
        "name": "铰接油缸A行程(mm)",
        "value": "100"
      },
      {
        "name": "铰接油缸B行程(mm)",
        "value": "100"
      },
      {
        "name": "铰接油缸C行程(mm)",
        "value": "100"
      },
      {
        "name": "铰接油缸D行程(mm)",
        "value": "100"
      },
      {
        "name": "铰接油缸压力(bar)",
        "value": "100"
      }
    ]
  },
  {
    "name": "同步注浆量",
    "type":1,
    "id":3,
    "son": [
      {
        "name": "1注浆压力(bar)",
        "value": "100"
      },
      {
        "name": "2注浆压力(bar)",
        "value": "100"
      },
      {
        "name": "3注浆压力(bar)",
        "value": "100"
      },
      {
        "name": "4注浆压力(bar)",
        "value": "100"
      },
      {
        "name": "1注浆量(strokes)",
        "value": "100"
      },
      {
        "name": "2注浆量(strokes)",
        "value": "100"
      },
      {
        "name": "3注浆量(strokes)",
        "value": "100"
      },
      {
        "name": "4注浆量(strokes)",
        "value": "100"
      }
    ]
  },
  {
    "name": "泡沫系统",
    "type":2,
    "id":4,
    "son": [
      {
        "name": "系统1压力(bar)",
        "value": "100"
      },
      {
        "name": "系统2压力(bar)",
        "value": "100"
      },
      {
        "name": "系统3压力(bar)",
        "value": "100"
      },
      {
        "name": "系统4压力(bar)",
        "value": "100"
      },
      {
        "name": "系统1空气流量(L/min)",
        "value": "100"
      },
      {
        "name": "系统2空气流量(L/min)",
        "value": "100"
      },
      {
        "name": "系统3空气流量(L/min)",
        "value": "100"
      },
      {
        "name": "系统4空气流量(L/min)",
        "value": "100"
      },
      {
        "name": "系统1添加剂流量(L/min)",
        "value": "100"
      },
      {
        "name": "系统2添加剂流量(L/min)",
        "value": "100"
      },
      {
        "name": "系统3添加剂流量(L/min)",
        "value": "100"
      },
      {
        "name": "系统4添加剂流量(L/min)",
        "value": "100"
      }
    ]
  },
  {
    "name":"掘进实时位置监控",
    "type":2,
    "id":5,
    "son":[
      {
        "name":"经度(度)",
        "value":100
      },
      {
        "name":"纬度(度)",
        "value":40
      },
      {
        "name":"高度(米)",
        "value":100
      },
      {
        "name":"相对地面高度(米)",
        "value":110
      }
    ]
  },
  {
    "name": "土压",
    "type":1,
    "id":6,
    "son": [
      {
        "name": "土压1(bar)",
        "value": 0.56
      },
      {
        "name": "土压2(bar)",
        "value": 0.56
      },
      {
        "name": "土压3(bar)",
        "value": 0.56
      },
      {
        "name": "土压4(bar)",
        "value": 0.56
      }
    ]
  }
]